xlwings/__init__.py
xlwings/_win32patch.py
xlwings/_xlmac.py
xlwings/_xlwindows.py
xlwings/base_classes.py
xlwings/cli.py
xlwings/com_server.py
xlwings/constants.py
xlwings/expansion.py
xlwings/mac_dict.py
xlwings/main.py
xlwings/quickstart.xlsm
xlwings/quickstart_addin.xlam
xlwings/quickstart_addin_ribbon.xlam
xlwings/quickstart_standalone.xlsm
xlwings/reports.py
xlwings/server.py
xlwings/udfs.py
xlwings/utils.py
xlwings/xlwings-0.33.20.applescript
xlwings/xlwings.bas
xlwings/xlwings_custom_addin.bas
xlwings/addin/Dictionary.cls
xlwings/addin/IWebAuthenticator.cls
xlwings/addin/Remote.bas
xlwings/addin/WebClient.cls
xlwings/addin/WebHelpers.bas
xlwings/addin/WebRequest.cls
xlwings/addin/WebResponse.cls
xlwings/addin/xlwings.xlam
xlwings/conversion/__init__.py
xlwings/conversion/framework.py
xlwings/conversion/numpy_conv.py
xlwings/conversion/pandas_conv.py
xlwings/conversion/polars_conv.py
xlwings/conversion/standard.py
xlwings/ext/__init__.py
xlwings/ext/sql.py
xlwings/html/xlwings-alert.html
xlwings/js/xlwings.js
xlwings/js/xlwings.ts
xlwings/pro/__init__.py
xlwings/pro/_xlcalamine.py
xlwings/pro/_xlofficejs.py
xlwings/pro/_xlremote.py
xlwings/pro/embedded_code.py
xlwings/pro/udfs_officejs.py
xlwings/pro/utils.py
xlwings/pro/reports/__init__.py
xlwings/pro/reports/filters.py
xlwings/pro/reports/image.py
xlwings/pro/reports/main.py
xlwings/pro/reports/markdown.py
xlwings/pro/reports/pdf.py
xlwings/rest/__init__.py
xlwings/rest/api.py
xlwings/rest/serializers.py
xlwings-0.33.20.dist-info/licenses/LICENSE.txt
xlwings-0.33.20.dist-info/licenses/LICENSE_PRO.txt
xlwings-0.33.20.dist-info/METADATA
xlwings-0.33.20.dist-info/WHEEL
xlwings-0.33.20.dist-info/entry_points.txt
xlwings-0.33.20.dist-info/top_level.txt
xlwings-0.33.20.dist-info/RECORD
