Metadata-Version: 2.3
Name: xlwings
Version: 0.33.20
Classifier: Development Status :: 4 - Beta
Classifier: Operating System :: OS Independent
Classifier: Programming Language :: Python
Classifier: Programming Language :: Python :: 3
Classifier: Programming Language :: Python :: 3.9
Classifier: Programming Language :: Python :: 3.10
Classifier: Programming Language :: Python :: 3.11
Classifier: Programming Language :: Python :: 3.12
Classifier: Programming Language :: Python :: 3.13
Classifier: Topic :: Office/Business :: Financial :: Spreadsheet
Classifier: License :: OSI Approved :: BSD License
Requires-Dist: pywin32 >=224 ; platform_system == 'Windows'
Requires-Dist: psutil >=2.0.0 ; platform_system == 'Darwin'
Requires-Dist: appscript >=1.0.1 ; platform_system == 'Darwin'
Requires-Dist: jinja2 ; extra == 'reports'
Requires-Dist: pdfrw ; extra == 'reports'
Requires-Dist: mistune ; extra == 'reports'
Requires-Dist: black ; extra == 'all'
Requires-Dist: isort ; extra == 'all'
Requires-Dist: jinja2 ; extra == 'all'
Requires-Dist: pandas ; extra == 'all'
Requires-Dist: matplotlib ; extra == 'all'
Requires-Dist: plotly ; extra == 'all'
Requires-Dist: flask ; extra == 'all'
Requires-Dist: requests ; extra == 'all'
Requires-Dist: pdfrw ; extra == 'all'
Requires-Dist: pytest ; extra == 'all'
Requires-Dist: mistune ; extra == 'all'
Requires-Dist: watchgod ; extra == 'vba_edit'
Provides-Extra: reports
Provides-Extra: all
Provides-Extra: vba_edit
License-File: LICENSE.txt
License-File: LICENSE_PRO.txt
Summary: Make Excel fly: Interact with Excel from Python and vice versa.
Keywords: xls,excel,spreadsheet,workbook,vba,macro
Author-email: Felix Zumstein <felix.zumstein@zoomeranalytics.com>
License: BSD 3-clause
Requires-Python: >=3.9
Project-URL: Homepage, https://www.xlwings.org
Project-URL: Documentation, https://docs.xlwings.org
Project-URL: Funding, https://www.xlwings.org/pricing
Project-URL: Source, https://github.com/xlwings/xlwings
Project-URL: Changelog, https://docs.xlwings.org/en/stable/whatsnew.html
